projects/pwm-generator/pwm_gen.v
// verilog kode for pwm generator med variabel pulsbredde
// to knapper brukes til å øke/redusere pulsbredden med 10%
module pwm_gen
    (
        clk,            // input: klokke 100MHz
        increase_duty,  // input: +
        decrease_duty,  // input: -
        PWM_OUT         // output: PWM 10Mhz
    );
    input clk;
    input increase_duty;
    input decrease_duty;
    output PWM_OUT;
    wire slow_clk_enable;           // slow clock enable for debouncing
    reg[27:0] counter_debounce=0;   // teller for debouncing
    wire tmp1,tmp2,duty_inc;        // midleritig flip-flop signal for debouncing av (+) knapp
    wire tmp3,tmp4,duty_dec;        // midlertidig flip-flop signal for debouncing av (-) knapp
    reg[3:0] counter_PWM=0;         // teller for å lage 10Mhz PWM signal
    reg[3:0] DUTY_CYCLE=5;          // pulsbredde starter på 50%

    // debouncer knappene for +/- pulsbredde
    // genererer først en sakte klokke for debouncing flip-flop (4Hz)
    always @(posedge clk)
        begin
            counter_debounce <= counter_debounce + 1;
            // kommenter ut for å kjøre på FPGA 
            //if(counter_debounce>=25000000) then

            // kommenter ut for å kjøre simulering
            if(counter_debounce>=1)
                counter_debounce <= 0;
        end
    // kommenter ut for å kjøre på FPGA
    // assign slow_clk_enable = counter_debounce == 25000000 ?1:0;
    
    // kommenter for å kjøre på FPGA
    assign slow_clk_enable = counter_debounce == 1 ?1:0;
    
    // debouncing av flip-flop for (+) knapp
    DFF_PWM PWM_DFF1(clk,slow_clk_enable,increase_duty,tmp1);
    DFF_PWM PWM_DFF2(clk,slow_clk_enable,tmp1, tmp2);
    assign duty_inc =  tmp1 & (~ tmp2) & slow_clk_enable;

    // debouncing av flip-flop for (-) knapp
    DFF_PWM PWM_DFF3(clk,slow_clk_enable,decrease_duty, tmp3);
    DFF_PWM PWM_DFF4(clk,slow_clk_enable,tmp3, tmp4);
    assign duty_dec =  tmp3 & (~ tmp4) & slow_clk_enable;

    // moduler pulsbredde med (+) eller (-) knapp
    always @(posedge clk)
        begin
            if(duty_inc==1 && DUTY_CYCLE <= 9)
                DUTY_CYCLE <= DUTY_CYCLE + 1;       // pulsbredde + 10%
            else if(duty_dec==1 && DUTY_CYCLE>=1)
                DUTY_CYCLE <= DUTY_CYCLE - 1;       // pulsbredde - 10%
        end
    
    // lag 10MHz PWM signal
    always @(posedge clk)
        begin
            counter_PWM <= counter_PWM + 1;
            if(counter_PWM>=9)
                counter_PWM <= 0;
        end
    assign PWM_OUT = counter_PWM < DUTY_CYCLE ? 1:0;
endmodule

// debounce flip-flop for knappene
module DFF_PWM(clk,en,D,Q);
    input clk,en,D;
    output reg Q;
    always @(posedge clk)
        begin
            if(en==1) // slow clock enable signal
                Q <= D;
        end
endmodule

projects/pwm-generator/pwm_gen_tb.v
`timescale 1ns / 1ps
`include "pwm_gen.v"

module tb_pwm_gen;
    // Inputs
    reg clk;
    reg increase_duty;
    reg decrease_duty;
    // Outputs
    wire PWM_OUT;
    // Instantiate the PWM Generator with variable duty cycle in Verilog
    pwm_gen pwm_generator_unit(
        .clk(clk),
        .increase_duty(increase_duty),
        .decrease_duty(decrease_duty),
        .PWM_OUT(PWM_OUT)
    );
    // Clock generation
    always #5 clk = ~clk;

    // Stimulus generation
    initial begin
        clk = 0;
        increase_duty = 0;
        decrease_duty = 0;

        $dumpfile("waveform.vcd"); // Specify the VCD file name
        $dumpvars(0, tb_pwm_gen); // Dump all signals in the module

        #100; // Wait for initial stabilization

        // Simulate button presses
        #10 increase_duty = 1; #10 increase_duty = 0; // increase duty cycle by 10%
        #10 increase_duty = 1; #10 increase_duty = 0; // increase duty cycle by 10%
        #10 increase_duty = 1; #10 increase_duty = 0; // increase duty cycle by 10%
        #10 decrease_duty = 1; #10 decrease_duty = 0; // decrease duty cycle by 10%
        #10 decrease_duty = 1; #10 decrease_duty = 0; // decrease duty cycle by 10%
        #10 decrease_duty = 1; #10 decrease_duty = 0; // decrease duty cycle by 10%
        #10 decrease_duty = 1; #10 decrease_duty = 0; // decrease duty cycle by 10%

        #100; // Wait for simulation to stabilize
        $finish; // End simulation
    end
endmodule

projects/pwm-generator/waveform.vcd
$date
	Sat Apr 13 13:45:37 2024
$end
$version
	Icarus Verilog
$end
$timescale
	1ps
$end
$scope module tb_pwm_gen $end
$var wire 1 ! PWM_OUT $end
$var reg 1 " clk $end
$var reg 1 # decrease_duty $end
$var reg 1 $ increase_duty $end
$scope module pwm_generator_unit $end
$var wire 1 " clk $end
$var wire 1 # decrease_duty $end
$var wire 1 % duty_dec $end
$var wire 1 & duty_inc $end
$var wire 1 $ increase_duty $end
$var wire 1 ' tmp4 $end
$var wire 1 ( tmp3 $end
$var wire 1 ) tmp2 $end
$var wire 1 * tmp1 $end
$var wire 1 + slow_clk_enable $end
$var wire 1 ! PWM_OUT $end
$var reg 4 , DUTY_CYCLE [3:0] $end
$var reg 4 - counter_PWM [3:0] $end
$var reg 28 . counter_debounce [27:0] $end
$scope module PWM_DFF1 $end
$var wire 1 $ D $end
$var wire 1 " clk $end
$var wire 1 + en $end
$var reg 1 * Q $end
$upscope $end
$scope module PWM_DFF2 $end
$var wire 1 * D $end
$var wire 1 " clk $end
$var wire 1 + en $end
$var reg 1 ) Q $end
$upscope $end
$scope module PWM_DFF3 $end
$var wire 1 # D $end
$var wire 1 " clk $end
$var wire 1 + en $end
$var reg 1 ( Q $end
$upscope $end
$scope module PWM_DFF4 $end
$var wire 1 ( D $end
$var wire 1 " clk $end
$var wire 1 + en $end
$var reg 1 ' Q $end
$upscope $end
$upscope $end
$upscope $end
$enddefinitions $end
$comment Show the parameter values. $end
$dumpall
$end
#0
$dumpvars
b0 .
b0 -
b101 ,
0+
x*
x)
x(
x'
0&
0%
0$
0#
0"
1!
$end
#5000
x%
x&
1+
b1 .
b1 -
1"
#10000
0"
#15000
0+
0%
0&
b10 -
b0 .
0(
0*
1"
#20000
0"
#25000
1+
b1 .
b11 -
1"
#30000
0"
#35000
0+
b100 -
b0 .
0'
0)
1"
#40000
0"
#45000
1+
0!
b1 .
b101 -
1"
#50000
0"
#55000
0+
b110 -
b0 .
1"
#60000
0"
#65000
1+
b1 .
b111 -
1"
#70000
0"
#75000
0+
b1000 -
b0 .
1"
#80000
0"
#85000
1+
b1 .
b1001 -
1"
#90000
0"
#95000
1!
0+
b0 -
b0 .
1"
#100000
0"
#105000
1+
b1 .
b1 -
1"
#110000
0"
1$
#115000
0+
0&
b10 -
b0 .
1*
1"
#120000
0"
0$
#125000
1&
1+
b1 .
b11 -
1"
#130000
0"
1$
#135000
0&
0+
b100 -
b110 ,
b0 .
1)
1"
#140000
0"
0$
#145000
1+
b1 .
b101 -
1"
#150000
0"
1$
#155000
0!
0+
b110 -
b0 .
1"
#160000
0"
0$
#165000
1+
b1 .
b111 -
1"
#170000
0"
1#
#175000
0+
0%
b1000 -
b0 .
1(
0*
1"
#180000
0"
0#
#185000
1%
1+
b1 .
b1001 -
1"
#190000
0"
1#
#195000
0%
1!
0+
b0 -
b101 ,
b0 .
1'
0)
1"
#200000
0"
0#
#205000
1+
b1 .
b1 -
1"
#210000
0"
1#
#215000
0+
b10 -
b0 .
1"
#220000
0"
0#
#225000
1+
b1 .
b11 -
1"
#230000
0"
1#
#235000
0+
b100 -
b0 .
1"
#240000
0"
0#
#245000
1+
0!
b1 .
b101 -
1"
#250000
0"
#255000
0+
b110 -
b0 .
0(
1"
#260000
0"
#265000
1+
b1 .
b111 -
1"
#270000
0"
#275000
0+
b1000 -
b0 .
0'
1"
#280000
0"
#285000
1+
b1 .
b1001 -
1"
#290000
0"
#295000
1!
0+
b0 -
b0 .
1"
#300000
0"
#305000
1+
b1 .
b1 -
1"
#310000
0"
#315000
0+
b10 -
b0 .
1"
#320000
0"
#325000
1+
b1 .
b11 -
1"
#330000
0"
#335000
0+
b100 -
b0 .
1"
